fast_pq/__init__.py
fast_pq/_fast_pq.cpp
fast_pq/_fast_pq.cpython-311-darwin.so
fast_pq/_transform.py
fast_pq/fast_pq.py
fast_pq/ivf.py
fast_pq-0.3.dist-info/LICENSE
fast_pq-0.3.dist-info/METADATA
fast_pq-0.3.dist-info/WHEEL
fast_pq-0.3.dist-info/top_level.txt
fast_pq-0.3.dist-info/RECORD
