Metadata-Version: 2.1
Name: fast-pq
Version: 0.3
Summary: Approximate Nearest Neighbors in Python.
Author-email: Thomas Dybdahl Ahle <lobais@gmail.com>
License: AGPL-3.0-or-later
Project-URL: homepage, https://github.com/thomasahle/fast_pq/
Keywords: nns,approximate nearest neighbor search
Classifier: Development Status :: 4 - Beta
Classifier: Intended Audience :: Developers
Classifier: Programming Language :: Python
Classifier: Programming Language :: Python :: 3.9
Classifier: Programming Language :: Python :: 3.10
Classifier: Programming Language :: Python :: 3.11
License-File: LICENSE
Requires-Dist: Cython (>=0.29)
Requires-Dist: numpy (>=1.24)
Requires-Dist: pytest (>=7.2)
Requires-Dist: scikit-learn (>=1.2)
